[{"title":"CentOS7安装Redis","url":"/2020/10/08/redis安装/"},{"title":"Oracle导入导出实践","url":"/2020/08/18/Oracle导入导出实践/"},{"title":"Linux 快捷键","url":"/2020/08/12/Linux-快捷键/"},{"title":"虚拟机安装RedHat6.5实践","url":"/2020/08/10/虚拟机安装RedHat6.5实践/"},{"title":"软件资源下载","url":"/2020/07/17/软件资源下载/"},{"title":"VMware虚拟机安装及使用","url":"/2020/07/17/VMware虚拟机安装/"},{"title":"Linux升级bash版本","url":"/2020/07/13/linux-bash升级/"},{"title":"Oracle11.2.0.4打补丁实践","url":"/2020/07/10/oracle-Opatch/"},{"title":"初识powershell","url":"/2020/06/06/devtool-powershell/"},{"title":"初识windows Terminal","url":"/2020/06/06/devtool-windowsTerminal/"},{"title":"利用Hexo在GitHub Page搭建博客","url":"/2020/05/21/blog-hexo/"},{"title":"PLSQL12使用","url":"/2019/11/06/devtool-plsql/"}]